fetch_ethercodes.py
fetch_ethercodes-0.5.dist-info/LICENSE.txt
fetch_ethercodes-0.5.dist-info/METADATA
fetch_ethercodes-0.5.dist-info/WHEEL
fetch_ethercodes-0.5.dist-info/entry_points.txt
fetch_ethercodes-0.5.dist-info/top_level.txt
fetch_ethercodes-0.5.dist-info/RECORD
