Metadata-Version: 2.1
Name: fetch-ethercodes
Version: 0.5
Summary: Fetch and generate ethercodes data for arpwatch
Home-page: https://github.com/frispete/fetch-ethercodes
Author: Hans-Peter Jansen
Author-email: <hpj@urpla.net>
License: MIT
Platform: UNKNOWN
Classifier: Development Status :: 5 - Production/Stable
Classifier: Intended Audience :: System Administrators
Classifier: License :: OSI Approved :: MIT License
Classifier: Programming Language :: Python :: 3.3
Classifier: Programming Language :: Python :: 3.4
Classifier: Programming Language :: Python :: 3.5
Classifier: Programming Language :: Python :: 3.6
Requires-Python: >=3
